package_operacoes/__init__.py
package_operacoes/funcoes.py
package_operacoes-0.0.3.dist-info/METADATA
package_operacoes-0.0.3.dist-info/WHEEL
package_operacoes-0.0.3.dist-info/top_level.txt
package_operacoes-0.0.3.dist-info/RECORD
