Metadata-Version: 2.1
Name: package-operacoes
Version: 0.0.3
Summary: Operações de Soma e Subtração
Home-page: https://github.com/laranelson/project_calc_package.git
Author: nelson_lara
Author-email: nelsonlarajr@gmail.com
License: UNKNOWN
Platform: UNKNOWN
Requires-Python: >=3.8
